text_numbered_list_analyser/__init__.py
text_numbered_list_analyser/text_numbered_list_analyser.py
text_numbered_list_analyser-1.1.0.dist-info/METADATA
text_numbered_list_analyser-1.1.0.dist-info/RECORD
text_numbered_list_analyser-1.1.0.dist-info/WHEEL
text_numbered_list_analyser-1.1.0.dist-info/top_level.txt
